nerdlog/__init__.py
nerdlog/logger.py
nerdlog-0.1.7.dist-info/DESCRIPTION.rst
nerdlog-0.1.7.dist-info/METADATA
nerdlog-0.1.7.dist-info/RECORD
nerdlog-0.1.7.dist-info/WHEEL
nerdlog-0.1.7.dist-info/metadata.json
nerdlog-0.1.7.dist-info/top_level.txt
