Metadata-Version: 2.0
Name: nerdlog
Version: 0.1.7
Summary: Simple logging library.
Home-page: UNKNOWN
Author: Magnus Hirth
Author-email: mhmorgan42@gmail.com
License: UNKNOWN
Platform: UNKNOWN
Classifier: Programming Language :: Python :: 3
